build/lib/build/lib/build/lib/build/lib/docs/source/conf.py
build/lib/build/lib/build/lib/build/lib/gamla/__init__.py
build/lib/build/lib/build/lib/build/lib/gamla/apply_test.py
build/lib/build/lib/build/lib/build/lib/gamla/apply_utils.py
build/lib/build/lib/build/lib/build/lib/gamla/currying.py
build/lib/build/lib/build/lib/build/lib/gamla/data.py
build/lib/build/lib/build/lib/build/lib/gamla/data_test.py
build/lib/build/lib/build/lib/build/lib/gamla/debug.py
build/lib/build/lib/build/lib/build/lib/gamla/debug_utils.py
build/lib/build/lib/build/lib/build/lib/gamla/dict_utils.py
build/lib/build/lib/build/lib/build/lib/gamla/dict_utils_test.py
build/lib/build/lib/build/lib/build/lib/gamla/excepts_decorator.py
build/lib/build/lib/build/lib/build/lib/gamla/excepts_decorator_test.py
build/lib/build/lib/build/lib/build/lib/gamla/functional.py
build/lib/build/lib/build/lib/build/lib/gamla/functional_async.py
build/lib/build/lib/build/lib/build/lib/gamla/functional_generic.py
build/lib/build/lib/build/lib/build/lib/gamla/functional_test.py
build/lib/build/lib/build/lib/build/lib/gamla/graph.py
build/lib/build/lib/build/lib/build/lib/gamla/graph_async.py
build/lib/build/lib/build/lib/build/lib/gamla/graph_test.py
build/lib/build/lib/build/lib/build/lib/gamla/higher_order.py
build/lib/build/lib/build/lib/build/lib/gamla/higher_order_test.py
build/lib/build/lib/build/lib/build/lib/gamla/io_utils.py
build/lib/build/lib/build/lib/build/lib/gamla/io_utils_test.py
build/lib/build/lib/build/lib/build/lib/gamla/string.py
build/lib/build/lib/build/lib/build/lib/gamla/transducer.py
build/lib/build/lib/build/lib/build/lib/gamla/transducer_test.py
build/lib/build/lib/build/lib/build/lib/gamla/tree.py
build/lib/build/lib/build/lib/build/lib/gamla/tree_test.py
build/lib/build/lib/build/lib/build/lib/gamla/url_utils.py
build/lib/build/lib/build/lib/build/lib/gamla/url_utils_test.py
build/lib/build/lib/build/lib/docs/source/conf.py
build/lib/build/lib/build/lib/gamla/__init__.py
gamla-72.dist-info/LICENSE
gamla-72.dist-info/METADATA
gamla-72.dist-info/WHEEL
gamla-72.dist-info/top_level.txt
gamla-72.dist-info/RECORD
