Metadata-Version: 2.1
Name: gamla
Version: 72
Summary: UNKNOWN
Home-page: UNKNOWN
License: UNKNOWN
Platform: UNKNOWN
Requires-Dist: async-timeout
Requires-Dist: dataclasses-json
Requires-Dist: heapq-max
Requires-Dist: httpx
Requires-Dist: pytest-asyncio
Requires-Dist: pytest
Requires-Dist: requests
Requires-Dist: toolz
